{"metadata": {"dbt_schema_version": "https://schemas.getdbt.com/dbt/run-results/v4.json", "dbt_version": "1.2.0", "generated_at": "2022-08-15T17:54:57.725310Z", "invocation_id": "04f496ed-bfca-4c26-8805-584564ba2744", "env": {}}, "results": [{"status": "success", "timing": [{"name": "compile", "started_at": "2022-08-15T17:54:49.022864Z", "completed_at": "2022-08-15T17:54:49.036616Z"}, {"name": "execute", "started_at": "2022-08-15T17:54:49.037558Z", "completed_at": "2022-08-15T17:54:51.702973Z"}], "thread_id": "Thread-1", "execution_time": 2.806525945663452, "adapter_response": {"_message": "SELECT", "code": "SELECT", "rows_affected": -1}, "message": "SELECT", "failures": null, "unique_id": "model.analytics_dbt.my_first_dbt_model"}, {"status": "success", "timing": [{"name": "compile", "started_at": "2022-08-15T17:54:51.842691Z", "completed_at": "2022-08-15T17:54:51.849820Z"}, {"name": "execute", "started_at": "2022-08-15T17:54:51.850828Z", "completed_at": "2022-08-15T17:54:54.056364Z"}], "thread_id": "Thread-1", "execution_time": 2.340104818344116, "adapter_response": {"_message": "CREATE VIEW", "code": "CREATE VIEW", "rows_affected": -1}, "message": "CREATE VIEW", "failures": null, "unique_id": "model.analytics_dbt.vw_sales"}, {"status": "success", "timing": [{"name": "compile", "started_at": "2022-08-15T17:54:54.194418Z", "completed_at": "2022-08-15T17:54:54.215225Z"}, {"name": "execute", "started_at": "2022-08-15T17:54:54.216000Z", "completed_at": "2022-08-15T17:54:56.321213Z"}], "thread_id": "Thread-1", "execution_time": 2.2511959075927734, "adapter_response": {"_message": "CREATE VIEW", "code": "CREATE VIEW", "rows_affected": -1}, "message": "CREATE VIEW", "failures": null, "unique_id": "model.analytics_dbt.my_second_dbt_model"}], "elapsed_time": 13.56650972366333, "args": {"write_json": true, "use_colors": true, "printer_width": 80, "version_check": true, "partial_parse": true, "static_parser": true, "profiles_dir": "/root/.dbt", "send_anonymous_usage_stats": true, "event_buffer_size": 100000, "quiet": false, "no_print": false, "which": "run", "rpc_method": "run", "indirect_selection": "eager"}}